dssatlm/__init__.py
dssatlm/envs.py
dssatlm/llm.py
dssatlm/pipeline.py
dssatlm/prompt_templates/dssatlm_full_template_as_interpreter.txt
dssatlm/prompt_templates/system_template_as_interpreter.txt
dssatlm/prompt_templates/system_template_as_interpreter_v0.txt
dssatlm/prompt_templates/system_template_as_parser.txt
dssatlm/prompt_templates/system_template_as_parser_for_q2s.txt
dssatlm/prompt_templates/user_template_for_interpreter.txt
dssatlm/prompt_templates/user_template_for_parser.txt
dssatlm/structured_components.py
dssatlm/structured_responses.py
dssatlm/textual_db/bank_of_definitions.txt
dssatlm/textual_db/bank_of_definitions_v0.txt
dssatlm/textual_db/bank_of_questions.txt
dssatlm/textual_db/sample_dssat_questions.csv
dssatlm/utils.py
dssatlm-0.1.12.dist-info/METADATA
dssatlm-0.1.12.dist-info/WHEEL
dssatlm-0.1.12.dist-info/RECORD
